{
    "uuid": [
        {
            "value": "125a78ce-fa13-4779-8468-9c165c04f497"
        }
    ],
    "langcode": [
        {
            "value": "en"
        }
    ],
    "shortcut_set": [
        {
            "target_id": "default",
            "target_type": "shortcut_set",
            "target_uuid": "cc7f29da-267b-463f-8498-adb11307ae14"
        }
    ],
    "title": [
        {
            "value": "Tome Static"
        }
    ],
    "weight": [
        {
            "value": 5
        }
    ],
    "link": [
        {
            "uri": "internal:\/admin\/config\/tome\/static",
            "title": null,
            "options": []
        }
    ],
    "default_langcode": [
        {
            "value": true
        }
    ]
}